uiuc_api/__init__.py
uiuc_api/course.py
uiuc_api/fetch.py
uiuc_api/parse.py
uiuc_api/prerequisites.lark
uiuc_api/utils.py
uiuc_api-0.1.4.dist-info/LICENSE
uiuc_api-0.1.4.dist-info/METADATA
uiuc_api-0.1.4.dist-info/WHEEL
uiuc_api-0.1.4.dist-info/top_level.txt
uiuc_api-0.1.4.dist-info/RECORD
