Metadata-Version: 2.1
Name: uiuc-api
Version: 0.1.4
Summary: A python wrapper for UIUC's official REST API for querying course data.
Home-page: https://gitlab.com/TimothyZhou/uiuc_api
Author: Timothy Zhou
License: UNKNOWN
Platform: UNKNOWN
Classifier: Programming Language :: Python :: 3
Classifier: License :: OSI Approved :: MIT License
Classifier: Operating System :: OS Independent
Requires-Python: >=3.6
Requires-Dist: requests
Requires-Dist: lxml
Requires-Dist: pyyaml
Requires-Dist: lark-parser
